.gitignore
BIP32.txt
CHANGES
COMMAND-LINE-TOOLS.md
CREDITS
LICENSE
MANIFEST.in
Makefile
README.md
TESTING.txt
pip-req.txt
pyproject.toml
setup.py
test.sh
tox.ini
.github/workflows/publish-to-test-pypi.yml
.github/workflows/test-py27.yml
.github/workflows/test.yml
docs/.gitignore
docs/Makefile
docs/api.rst
docs/bitcoin.rst
docs/cmdtools.rst
docs/conf.py
docs/index.rst
docs/install.rst
docs/make.bat
docs/source/contract.rst
docs/source/pycoin.ecdsa.rst
docs/source/pycoin.services.rst
docs/source/recipes.rst
pycoin/__init__.py
pycoin/block.py
pycoin/bloomfilter.py
pycoin/intbytes.py
pycoin/merkle.py
pycoin.egg-info/PKG-INFO
pycoin.egg-info/SOURCES.txt
pycoin.egg-info/dependency_links.txt
pycoin.egg-info/entry_points.txt
pycoin.egg-info/top_level.txt
pycoin/blockchain/BlockChain.py
pycoin/blockchain/ChainFinder.py
pycoin/blockchain/__init__.py
pycoin/cmds/__init__.py
pycoin/cmds/b58.py
pycoin/cmds/block.py
pycoin/cmds/coinc.py
pycoin/cmds/dump.py
pycoin/cmds/keychain.py
pycoin/cmds/ku.py
pycoin/cmds/msg.py
pycoin/cmds/tx.py
pycoin/coins/SolutionChecker.py
pycoin/coins/Tx.py
pycoin/coins/TxIn.py
pycoin/coins/TxOut.py
pycoin/coins/__init__.py
pycoin/coins/exceptions.py
pycoin/coins/tx_utils.py
pycoin/coins/bcash/Block.py
pycoin/coins/bcash/SolutionChecker.py
pycoin/coins/bcash/Solver.py
pycoin/coins/bcash/Tx.py
pycoin/coins/bcash/__init__.py
pycoin/coins/bgold/Block.py
pycoin/coins/bgold/SolutionChecker.py
pycoin/coins/bgold/Solver.py
pycoin/coins/bgold/Tx.py
pycoin/coins/bgold/__init__.py
pycoin/coins/bitcoin/P2SChecker.py
pycoin/coins/bitcoin/ScriptStreamer.py
pycoin/coins/bitcoin/ScriptTools.py
pycoin/coins/bitcoin/SegwitChecker.py
pycoin/coins/bitcoin/SolutionChecker.py
pycoin/coins/bitcoin/Solver.py
pycoin/coins/bitcoin/Spendable.py
pycoin/coins/bitcoin/Tx.py
pycoin/coins/bitcoin/TxIn.py
pycoin/coins/bitcoin/TxOut.py
pycoin/coins/bitcoin/VM.py
pycoin/coins/bitcoin/__init__.py
pycoin/coins/bitcoin/make_instruction_lookup.py
pycoin/coins/groestlcoin/Block.py
pycoin/coins/groestlcoin/SolutionChecker.py
pycoin/coins/groestlcoin/Solver.py
pycoin/coins/groestlcoin/Tx.py
pycoin/coins/groestlcoin/__init__.py
